{
  "basics": {
    "name": "Katamori",
    "label": "",
    "picture": "https://robohash.org/fe112c322d16dffee6135f6f36f1aab3",
    "email": "katamorihun@protonmail.com",
    "phone": "",
    "website": "",
    "summary": "Welcome! <br><br> I am Katamori, though not too active here anymore. All I do here is hosting a bunch of stuff I thought was important. Feel free to take a look around anyways!<br><br><a href='./deep-space-blizzard/index.html' target='_blank'>Deep Space Blizzard Wiki</a><br><br><a href='./voidshard/index.html' target='_blank'>Voidshard Wiki</a><br><br><a href='./terminus-nation' target='_blank'>Very old stuff I/we made for Terminus Nation</a>",
    "location": {
      "address": "",
      "postalCode": "",
      "city": "",
      "countryCode": "",
      "region": ""
    },
    "profiles": [
      {
        "network": "github",
        "username": "katamori",
        "url": "http://github.com/Katamori"
      }
    ]
  },
  "interests": [

  ],
  "skills": [

  ],
  "education": [

  ],
  "work": [

  ]
}